ecommerce_alipay_sdk/__init__.py
ecommerce_alipay_sdk/api.py
ecommerce_alipay_sdk/compability.py
ecommerce_alipay_sdk/config.py
ecommerce_alipay_sdk/exceptions.py
ecommerce_alipay_sdk/invoices.py
ecommerce_alipay_sdk/notifications.py
ecommerce_alipay_sdk/openid_connect.py
ecommerce_alipay_sdk/payment_experience.py
ecommerce_alipay_sdk/payments.py
ecommerce_alipay_sdk/resource.py
ecommerce_alipay_sdk/util.py
ecommerce_alipay_sdk/vault.py
ecommerce_alipay_sdk-0.0.4.dist-info/DESCRIPTION.rst
ecommerce_alipay_sdk-0.0.4.dist-info/METADATA
ecommerce_alipay_sdk-0.0.4.dist-info/RECORD
ecommerce_alipay_sdk-0.0.4.dist-info/WHEEL
ecommerce_alipay_sdk-0.0.4.dist-info/metadata.json
ecommerce_alipay_sdk-0.0.4.dist-info/top_level.txt
