Metadata-Version: 2.0
Name: ecommerce-alipay-sdk
Version: 0.0.4
Summary: An unofficial AliPay unofficial SDK for ecommerce module of edx
Home-page: https://github.com/seaswander/ecommerce-alipay-sdk
Author: seaswander
Author-email: sevenseaswander@gmail.com
License: MIT License
Keywords: ecommerce,alipay,ecommerce-alipay
Platform: any
Classifier: Development Status :: 3 - Alpha
Classifier: Intended Audience :: Developers
Classifier: Topic :: Software Development :: Build Tools
Classifier: License :: OSI Approved :: MIT License
Classifier: Programming Language :: Python :: 2.7
Requires-Dist: pycryptodome
Requires-Dist: six
